config_handler/__init__.py
config_handler/cli.py
config_handler/config_file.py
config_handler/constants.py
config_handler/exceptions.py
config_handler/handler.py
Config_Handler-0.1.0.dist-info/LICENSE
Config_Handler-0.1.0.dist-info/METADATA
Config_Handler-0.1.0.dist-info/WHEEL
Config_Handler-0.1.0.dist-info/entry_points.txt
Config_Handler-0.1.0.dist-info/top_level.txt
Config_Handler-0.1.0.dist-info/RECORD
