Metadata-Version: 2.1
Name: Config-Handler
Version: 0.1.0
Summary: Handle config files in your projects the easy way
Home-page: https://github.com/amphinicy/config-handler.git
Author: Amphinicy Technologies ltd
Author-email: info@amphinicy.com
License: MIT
Project-URL: Source, https://github.com/amphinicy/config-handler.git
Keywords: config,config-handler,python,json
Platform: UNKNOWN
Classifier: Development Status :: 4 - Beta
Classifier: Intended Audience :: Developers
Classifier: Topic :: Software Development :: Build Tools
Classifier: License :: OSI Approved :: MIT License
Classifier: Programming Language :: Python :: 3.7
Requires-Dist: click (~=7.0)
